<?xml version="1.0" encoding="utf-8" ?>
<XnaContent>
  <Asset Type="Library.Item[]">
    <!-- [0] -->
    <Item>
      <name>null</name>
      <isPickable>false</isPickable>
      <description>nothing</description>
      <textureString>Images/Sprites/null</textureString>
      <isCombinable>false</isCombinable>
      <combinedItemInt>2</combinedItemInt>
    </Item>
    <!-- [1] -->
    <Item>
      <name>Parachute</name>
      <isPickable>true</isPickable>
      <description>A packed parachute</description>
      <textureString>Images/Sprites/parachute</textureString>
      <isCombinable>false</isCombinable>
      <combinedItemInt>3</combinedItemInt>
    </Item>    
    <!-- [2] -->
    <Item>
      <name>Vine</name>
      <isPickable>true</isPickable>
      <description>Ooh. It's stretchy</description>
      <textureString>Images/Sprites/vine</textureString>
      <isCombinable>true</isCombinable>
      <combinedItemInt>4</combinedItemInt>
    </Item>    
    <!-- [3] -->
    <Item>
      <name>Twig</name>
      <isPickable>true</isPickable>
      <description>Neat! A twig!</description>
      <textureString>Images/Sprites/twig</textureString>
      <isCombinable>true</isCombinable>
      <combinedItemInt>4</combinedItemInt>
    </Item>    
    <!-- [4] -->
    <Item>
      <name>Slingshot</name>
      <isPickable>true</isPickable>
      <description>An unloaded slingshot</description>
      <textureString>Images/Sprites/unldsling</textureString>
      <isCombinable>true</isCombinable>
      <combinedItemInt>6</combinedItemInt>
    </Item>
    <!-- [5] -->   
    <Item>
      <name>Pebble</name>
      <isPickable>true</isPickable>
      <description>A small pebble</description>
      <textureString>Images/Sprites/pebble</textureString>
      <isCombinable>true</isCombinable>
      <combinedItemInt>6</combinedItemInt>
    </Item>    
    <!-- [6] -->   
    <Item>
      <name>Loaded slingshot</name>
      <isPickable>true</isPickable>
      <description>A loaded slingshot</description>
      <textureString>Images/Sprites/ldsling</textureString>
      <isCombinable>false</isCombinable>
      <combinedItemInt>1</combinedItemInt>
    </Item>
    <!-- [7] -->
    <Item>
      <name>Trash can</name>
      <isPickable>false</isPickable>
      <description>Someone put a trashcan here. Weird</description>
      <textureString>Images/Sprites/trashcan</textureString>
      <isCombinable>false</isCombinable>
      <combinedItemInt>1</combinedItemInt>
    </Item>    
    <!-- [8] -->
    <Item>
      <name>Empty bottle</name>
      <isPickable>true</isPickable>
      <description>An empty water bottle</description>
      <textureString>Images/Sprites/emptybottle</textureString>
      <isCombinable>false</isCombinable>
      <combinedItemInt>1</combinedItemInt>
    </Item>    
    <!-- [9] -->
    <Item>
      <name>Water bottle</name>
      <isPickable>true</isPickable>
      <description>A bottle of water</description>
      <textureString>Images/Sprites/filledbottle</textureString>
      <isCombinable>false</isCombinable>
      <combinedItemInt>1</combinedItemInt>
    </Item>
    <!-- [10] -->     
    <Item>
      <name>Wad of dough</name>
      <isPickable>true</isPickable>
      <description>Cash money</description>
      <textureString>Images/Sprites/money</textureString>
      <isCombinable>false</isCombinable>
      <combinedItemInt>1</combinedItemInt>
    </Item>      
  </Asset>
</XnaContent>
